{
	"name": "IncrementalLoad_AmedeoTolace_copy1",
	"properties": {
		"activities": [
			{
				"name": "GetLastLoad",
				"type": "Lookup",
				"dependsOn": [],
				"policy": {
					"timeout": "0.12:00:00",
					"retry": 0,
					"retryIntervalInSeconds": 30,
					"secureOutput": false,
					"secureInput": false
				},
				"userProperties": [],
				"typeProperties": {
					"source": {
						"type": "AzureSqlSource",
						"sqlReaderQuery": "@concat(\n'SELECT COALESCE(LastLoad,''01/01/1900'') AS LastLoad\nFROM ETL.LoadMeta\nWHERE Owner=''', pipeline().parameters.owner, ''' and \nTableName=''', pipeline().nome_tabella, ''' '\n)",
						"queryTimeout": "02:00:00",
						"partitionOption": "None"
					},
					"dataset": {
						"referenceName": "dat_db_DynamicTable",
						"type": "DatasetReference",
						"parameters": {
							"schema": "ETL",
							"table": "LoadMeta"
						}
					}
				}
			},
			{
				"name": "Set LastLoad",
				"type": "SetVariable",
				"dependsOn": [
					{
						"activity": "GetLastLoad",
						"dependencyConditions": [
							"Succeeded"
						]
					}
				],
				"userProperties": [],
				"typeProperties": {
					"variableName": "LastLoad",
					"value": {
						"value": "@activity('GetLastLoad').output.firstRow.LastLoad",
						"type": "Expression"
					}
				}
			},
			{
				"name": "IncrementalLoad",
				"type": "Copy",
				"dependsOn": [
					{
						"activity": "Set LastLoad",
						"dependencyConditions": [
							"Succeeded"
						]
					}
				],
				"policy": {
					"timeout": "0.12:00:00",
					"retry": 0,
					"retryIntervalInSeconds": 30,
					"secureOutput": false,
					"secureInput": false
				},
				"userProperties": [],
				"typeProperties": {
					"source": {
						"type": "AzureSqlSource",
						"sqlReaderQuery": {
							"value": "@concat('select * from SalesLT.'\n,pipeline().parameters.nome_tabella\n,' where ModifiedDate > '''\n,variables('LastLoad')\n,''''\n)",
							"type": "Expression"
						},
						"queryTimeout": "02:00:00",
						"partitionOption": "None"
					},
					"sink": {
						"type": "AzureSqlSink",
						"writeBehavior": "insert",
						"sqlWriterUseTableLock": false
					},
					"enableStaging": false,
					"translator": {
						"type": "TabularTranslator",
						"typeConversion": true,
						"typeConversionSettings": {
							"allowDataTruncation": true,
							"treatBooleanAsNumber": false
						}
					}
				},
				"inputs": [
					{
						"referenceName": "ADW_Table",
						"type": "DatasetReference",
						"parameters": {
							"schema": "test",
							"table": "test"
						}
					}
				],
				"outputs": [
					{
						"referenceName": "dat_db_DynamicTable",
						"type": "DatasetReference",
						"parameters": {
							"schema": "ETL",
							"table": "SalesOrderDetail"
						}
					}
				]
			},
			{
				"name": "Final Update",
				"type": "Script",
				"dependsOn": [
					{
						"activity": "Set MaxModifiedDate",
						"dependencyConditions": [
							"Succeeded"
						]
					}
				],
				"policy": {
					"timeout": "0.12:00:00",
					"retry": 0,
					"retryIntervalInSeconds": 30,
					"secureOutput": false,
					"secureInput": false
				},
				"userProperties": [],
				"linkedServiceName": {
					"referenceName": "dat_db",
					"type": "LinkedServiceReference"
				},
				"typeProperties": {
					"scripts": [
						{
							"type": "Query",
							"text": {
								"value": "@concat('update ETL.LoadMeta set LastLoad = ''',\nvariables('MaxModifiedDate'),\n''' where Owner = ''AmedeoTolace'' and TableName = ''',\npipeline().parameters.nome_tabella,\n''''\n)",
								"type": "Expression"
							}
						}
					],
					"scriptBlockExecutionTimeout": "02:00:00"
				}
			},
			{
				"name": "GetMaxModifiedDate",
				"type": "Lookup",
				"dependsOn": [
					{
						"activity": "IncrementalLoad",
						"dependencyConditions": [
							"Succeeded"
						]
					}
				],
				"policy": {
					"timeout": "0.12:00:00",
					"retry": 0,
					"retryIntervalInSeconds": 30,
					"secureOutput": false,
					"secureInput": false
				},
				"userProperties": [],
				"typeProperties": {
					"source": {
						"type": "AzureSqlSource",
						"sqlReaderQuery": {
							"value": "@concat('select max(ModifiedDate) as MaxModifiedDate from ETL.',pipeline().parameters.nome_tabella)",
							"type": "Expression"
						},
						"queryTimeout": "02:00:00",
						"partitionOption": "None"
					},
					"dataset": {
						"referenceName": "dat_db_DynamicTable",
						"type": "DatasetReference",
						"parameters": {
							"schema": "ETL",
							"table": "SalesOrderDetail"
						}
					},
					"firstRowOnly": true
				}
			},
			{
				"name": "Set MaxModifiedDate",
				"type": "SetVariable",
				"dependsOn": [
					{
						"activity": "GetMaxModifiedDate",
						"dependencyConditions": [
							"Succeeded"
						]
					}
				],
				"userProperties": [],
				"typeProperties": {
					"variableName": "MaxModifiedDate",
					"value": {
						"value": "@activity('GetMaxModifiedDate').output.firstRow.MaxModifiedDate",
						"type": "Expression"
					}
				}
			}
		],
		"parameters": {
			"nome_tabella": {
				"type": "string",
				"defaultValue": "SalesOrderDetail"
			},
			"owner": {
				"type": "string",
				"defaultValue": "AmedeoTolace"
			}
		},
		"variables": {
			"LastLoad": {
				"type": "String"
			},
			"MaxModifiedDate": {
				"type": "String"
			}
		},
		"folder": {
			"name": "AmedeoTolace"
		},
		"annotations": [],
		"lastPublishTime": "2023-03-18T10:06:40Z"
	},
	"type": "Microsoft.DataFactory/factories/pipelines"
}